{
    "realm": "reports-realm",
    "enabled": true,
    "roles": {
      "realm": [
        {
          "name": "user",
          "description": "Regular user role"
        },
        {
          "name": "administrator",
          "description": "Administrator role"
        },
        {
          "name": "prothetic_user",
          "description": "Prothetic user role with report access"
        }
      ]
    },
    "users": [
      {
        "username": "user1",
        "enabled": true,
        "email": "user1@example.com",
        "firstName": "User",
        "lastName": "One",
        "credentials": [
          {
            "type": "password",
            "value": "password123",
            "temporary": false
          }
        ],
        "realmRoles": ["user"]
      },
      {
        "username": "user2",
        "enabled": true,
        "email": "user2@example.com",
        "firstName": "User",
        "lastName": "Two",
        "credentials": [
          {
            "type": "password",
            "value": "password123",
            "temporary": false
          }
        ],
        "realmRoles": ["user"]
      },
      {
        "username": "admin1",
        "enabled": true,
        "email": "admin1@example.com",
        "firstName": "Admin",
        "lastName": "One",
        "credentials": [
          {
            "type": "password",
            "value": "admin123",
            "temporary": false
          }
        ],
        "realmRoles": ["administrator"]
      },
      {
        "username": "maria.sidorova",
        "enabled": true,
        "email": "maria.sidorova@bionicpro.com",
        "firstName": "Мария",
        "lastName": "Сидорова",
        "credentials": [
          {
            "type": "password",
            "value": "password123",
            "temporary": false
          }
        ],
        "realmRoles": ["prothetic_user"]
      },
      {
        "username": "alexei.ivanov",
        "enabled": true,
        "email": "alexei.ivanov@bionicpro.com",
        "firstName": "Алексей",
        "lastName": "Иванов",
        "credentials": [
          {
            "type": "password",
            "value": "password123",
            "temporary": false
          }
        ],
        "realmRoles": ["prothetic_user"]
      },
      {
        "username": "ivan.petrov",
        "enabled": true,
        "email": "ivan.petrov@bionicpro.com",
        "firstName": "Иван",
        "lastName": "Петров",
        "credentials": [
          {
            "type": "password",
            "value": "password123",
            "temporary": false
          }
        ],
        "realmRoles": ["prothetic_user"]
      }
    ],
    "clients": [
      {
        "clientId": "reports-frontend",
        "enabled": true,
        "publicClient": true,
        "redirectUris": ["http://localhost:3000/*"],
        "webOrigins": ["http://localhost:3000"],
        "directAccessGrantsEnabled": true,
        "attributes": {
          "pkce.code.challenge.method": "S256"
        }
      },
      {
        "clientId": "reports-api",
        "enabled": true,
        "clientAuthenticatorType": "client-secret",
        "secret": "oNwoLQdvJAvRcL89SydqCWCe5ry1jMgq", 
        "bearerOnly": true
      }
    ]
  }